{
	"Version": 3,
	"FileReferences": {
		"Moc": "kaia.moc3",
		"Textures": [
			"kaia.2048/texture_00.png"
		],
		"Physics": "kaia.physics3.json",
		"Pose": "kaia.pose3.json",
		"DisplayInfo": "kaia.cdi3.json",
		"Expressions": [
			{
				"Name": "default1",
				"File": "expressions/idle/default1.exp3.json"
			},
			{
				"Name": "happy1",
				"File": "expressions/happy/happy1.exp3.json"
			},
			{
				"Name": "happy2",
				"File": "expressions/happy/happy2.exp3.json"
			},
			{
				"Name": "smile1",
				"File": "expressions/happy/smile1.exp3.json"
			},
			{
				"Name": "smile2",
				"File": "expressions/happy/smile2.exp3.json"
			},
			{
				"Name": "shy1",
				"File": "expressions/shy/shy1.exp3.json"
			},
			{
				"Name": "shy2",
				"File": "expressions/shy/shy2.exp3.json"
			},
			{
				"Name": "angry1.exp3.json",
				"File": "expressions/angry/angry1.exp3.json"
			},
			{
				"Name": "angry2.exp3.json",
				"File": "expressions/angry/angry2.exp3.json"
			},
			{
				"Name": "listening1.exp3.json",
				"File": "expressions/listening/listening1.exp3.json"
			},
			{
				"Name": "listening2.exp3.json",
				"File": "expressions/listening/listening2.exp3.json"
			}
		],
		"Motions": {
			"Idle": [
				{
					"File": "motions/idle/idle1.motion3.json",
					"FadeInTime": 0.5,
					"FadeOutTime": 0.5
				},
				{
					"File": "motions/idle/idle2.motion3.json",
					"FadeInTime": 0.5,
					"FadeOutTime": 0.5
				},
				{
					"File": "motions/idle/idle3.motion3.json",
					"FadeInTime": 0.5,
					"FadeOutTime": 0.5
				},
				{
					"File": "motions/idle/default.motion3.json",
					"FadeInTime": 0.5,
					"FadeOutTime": 0.5
				}
			],
			"TapBody": [
				{
					"File": "motions/headtap/bamboozled1.motion3.json",
					"FadeInTime": 0.5,
					"FadeOutTime": 0.5
				}
			],
			"TapHead": [
				{
					"File": "motions/headtap/headtap1.motion3.json",
					"FadeInTime": 0.5,
					"FadeOutTime": 0.5
				},
				{
					"File": "motions/headtap/headtap2.motion3.json",
					"FadeInTime": 0.5,
					"FadeOutTime": 0.5
				}
			],
			"Affirmation": [
				{
					"File": "motions/affirmative/affirmative1.motion3.json",
					"FadeInTime": 0.5,
					"FadeOutTime": 0.5
				},
				{
					"File": "motions/affirmative/affirmative2.motion3.json",
					"FadeInTime": 0.5,
					"FadeOutTime": 0.5
				}
			],
			"Asking": [
				{
					"File": "motions/asking/ask1.motion3.json",
					"FadeInTime": 0.5,
					"FadeOutTime": 0.5
				}
			],
			"Negative": [
				{
					"File": "motions/negative/no1.motion3.json",
					"FadeInTime": 0.5,
					"FadeOutTime": 0.5
				}
			],
			"Speaking": [
				{
					"File": "motions/speaking/speaking1.motion3.json",
					"FadeInTime": 0.5,
					"FadeOutTime": 0.5
				},
				{
					"File": "motions/speaking/speaking2.motion3.json",
					"FadeInTime": 0.5,
					"FadeOutTime": 0.5
				}
			],
			"Switch": [
				{
					"File": "motions/switch/switch.motion3.json",
					"FadeInTime": 0.5,
					"FadeOutTime": 0.5
				}
			],
			"Sleep": [
				{
					"File": "motions/sleep/sleep.motion3.json",
					"FadeInTime": 0.5,
					"FadeOutTime": 0.5
				}
			],
			"Thinking": [
				{
					"File": "motions/thinking/notfound.motion3.json",
					"FadeInTime": 0.5,
					"FadeOutTime": 0.5
				},
				{
					"File": "motions/thinking/thinking.motion3.json",
					"FadeInTime": 0.5,
					"FadeOutTime": 0.5
				}
			]
		}
	},
	"Groups": [
		{
			"Target": "Parameter",
			"Name": "LipSync",
			"Ids": [
				"ParamMouthOpenY"
			]
		},
		{
			"Target": "Parameter",
			"Name": "LipForm",
			"Ids": [
				"ParamMouthForm"
			]
		},
		{
			"Target": "Parameter",
			"Name": "EyeBlink",
			"Ids": [
				"EyeLOpen",
				"EyeROpen"
			]
		}
	],
	"HitAreas": [
		{
			"Id": "HitArea",
			"Name": "Head"
		},
		{
			"Id": "HitArea2",
			"Name": "Drone"
		},
		{
			"Id": "HitArea3",
			"Name": "Body"
		},
		{
			"Id": "HitArea4",
			"Name": "Clipboard"
		},
		{
			"Id": "HitArea5",
			"Name": "Legs"
		}
	]
}